{
  "EC3A0F75-C0D1-4193-A3C3-07639888FCF8" : {
    "objectMetadataList" : [
      [
        "EC3A0F75-C0D1-4193-A3C3-07639888FCF8",
        "Root",
        "Material"
      ],
      {
        "isExpanded" : true,
        "isLocked" : false
      },
      [
        "EC3A0F75-C0D1-4193-A3C3-07639888FCF8",
        "Root"
      ],
      {
        "isExpanded" : true,
        "isLocked" : false
      }
    ]
  },
  "ED5D6B31-B089-42D4-A613-0626899E0FA2" : {
    "objectMetadataList" : [
      [
        "ED5D6B31-B089-42D4-A613-0626899E0FA2",
        "Root",
        "Earth_And_Ornaments",
        "Earth"
      ],
      {
        "isExpanded" : true,
        "isLocked" : false
      },
      [
        "ED5D6B31-B089-42D4-A613-0626899E0FA2",
        "Root",
        "Earth_And_Ornaments",
        "Poles",
        "DefaultMaterial"
      ],
      {
        "isExpanded" : true,
        "isLocked" : false
      },
      [
        "ED5D6B31-B089-42D4-A613-0626899E0FA2",
        "Root",
        "Earth",
        "geom",
        "realistic",
        "geo",
        "lod0"
      ],
      {
        "isExpanded" : true,
        "isLocked" : false
      },
      [
        "ED5D6B31-B089-42D4-A613-0626899E0FA2",
        "Root",
        "Earth_And_Ornaments",
        "Equator",
        "EquatorMaterial"
      ],
      {
        "isExpanded" : true,
        "isLocked" : false
      },
      [
        "ED5D6B31-B089-42D4-A613-0626899E0FA2",
        "Root",
        "Group",
        "Sphere",
        "Material",
        "dayNightAlphaMix"
      ],
      {
        "isExpanded" : true,
        "isLocked" : false
      },
      [
        "ED5D6B31-B089-42D4-A613-0626899E0FA2",
        "Root",
        "Earth",
        "geom",
        "realistic",
        "materials"
      ],
      {
        "isExpanded" : true,
        "isLocked" : false
      },
      [
        "ED5D6B31-B089-42D4-A613-0626899E0FA2",
        "Root",
        "Earth_And_Ornaments",
        "Poles"
      ],
      {
        "isExpanded" : true,
        "isLocked" : false
      },
      [
        "ED5D6B31-B089-42D4-A613-0626899E0FA2",
        "Root",
        "Group",
        "Poles",
        "DefaultMaterial"
      ],
      {
        "isExpanded" : true,
        "isLocked" : false
      },
      [
        "ED5D6B31-B089-42D4-A613-0626899E0FA2",
        "Root",
        "EarthMaterial",
        "textureCoordTimeOffset"
      ],
      {
        "isExpanded" : true,
        "isLocked" : false
      },
      [
        "ED5D6B31-B089-42D4-A613-0626899E0FA2",
        "Root",
        "Group",
        "Equator",
        "EquatorMaterial",
        "Distance"
      ],
      {
        "isExpanded" : true,
        "isLocked" : false
      },
      [
        "ED5D6B31-B089-42D4-A613-0626899E0FA2",
        "Root",
        "Group",
        "Sphere",
        "EarthMaterial",
        "dayNightAlphaMix"
      ],
      {
        "isExpanded" : true,
        "isLocked" : false
      },
      [
        "ED5D6B31-B089-42D4-A613-0626899E0FA2",
        "Root",
        "Earth_And_Ornaments",
        "Equator",
        "EquatorMaterial",
        "Distance"
      ],
      {
        "isExpanded" : true,
        "isLocked" : false
      },
      [
        "ED5D6B31-B089-42D4-A613-0626899E0FA2",
        "Root",
        "Group",
        "Equator",
        "DefaultMaterial",
        "Distance"
      ],
      {
        "isExpanded" : true,
        "isLocked" : false
      },
      [
        "ED5D6B31-B089-42D4-A613-0626899E0FA2",
        "Root",
        "Earth_And_Ornaments"
      ],
      {
        "isExpanded" : true,
        "isLocked" : false
      },
      [
        "ED5D6B31-B089-42D4-A613-0626899E0FA2",
        "Root",
        "Group",
        "Equator"
      ],
      {
        "isExpanded" : true,
        "isLocked" : false
      },
      [
        "ED5D6B31-B089-42D4-A613-0626899E0FA2",
        "Root",
        "Group",
        "Earth"
      ],
      {
        "isExpanded" : true,
        "isLocked" : false
      },
      [
        "ED5D6B31-B089-42D4-A613-0626899E0FA2",
        "EarthMaterial",
        "dayNightAlphaMix"
      ],
      {
        "isExpanded" : true,
        "isLocked" : false
      },
      [
        "ED5D6B31-B089-42D4-A613-0626899E0FA2",
        "Root",
        "Earth",
        "geom",
        "realistic"
      ],
      {
        "isExpanded" : true,
        "isLocked" : false
      },
      [
        "ED5D6B31-B089-42D4-A613-0626899E0FA2",
        "Root"
      ],
      {
        "isExpanded" : true,
        "isLocked" : false
      },
      [
        "ED5D6B31-B089-42D4-A613-0626899E0FA2",
        "Root",
        "Group",
        "Equator",
        "EquatorMaterial"
      ],
      {
        "isExpanded" : true,
        "isLocked" : false
      },
      [
        "ED5D6B31-B089-42D4-A613-0626899E0FA2",
        "Root",
        "EarthMaterial",
        "dayNightAlphaMix"
      ],
      {
        "isExpanded" : true,
        "isLocked" : false
      },
      [
        "ED5D6B31-B089-42D4-A613-0626899E0FA2",
        "Root",
        "Earth",
        "geom"
      ],
      {
        "isExpanded" : true,
        "isLocked" : false
      },
      [
        "ED5D6B31-B089-42D4-A613-0626899E0FA2",
        "Root",
        "Earth",
        "geom",
        "realistic",
        "geo"
      ],
      {
        "isExpanded" : true,
        "isLocked" : false
      },
      [
        "ED5D6B31-B089-42D4-A613-0626899E0FA2",
        "Root",
        "Earth_And_Ornaments",
        "Earth",
        "EarthMaterial"
      ],
      {
        "isExpanded" : true,
        "isLocked" : false
      },
      [
        "ED5D6B31-B089-42D4-A613-0626899E0FA2",
        "Root",
        "Group",
        "Poles"
      ],
      {
        "isExpanded" : true,
        "isLocked" : false
      },
      [
        "ED5D6B31-B089-42D4-A613-0626899E0FA2",
        "Root",
        "Sphere",
        "Material"
      ],
      {
        "isExpanded" : true,
        "isLocked" : false
      },
      [
        "ED5D6B31-B089-42D4-A613-0626899E0FA2",
        "Root",
        "Earth_And_Ornaments",
        "Equator"
      ],
      {
        "isExpanded" : true,
        "isLocked" : false
      }
    ]
  }
}